vrdata/__init__.py
vrdata/connector.py
vrdata-0.0.1.dist-info/LICENSE
vrdata-0.0.1.dist-info/METADATA
vrdata-0.0.1.dist-info/WHEEL
vrdata-0.0.1.dist-info/top_level.txt
vrdata-0.0.1.dist-info/RECORD
