Metadata-Version: 2.1
Name: vrdata
Version: 0.0.1
Summary: Enables connection to Viarezo Data Services.
Home-page: http://vrdata.viarezo.fr
Author: Faruk Hammoud
Author-email: farukhammoud@student-cs.fr
License: UNKNOWN
Platform: UNKNOWN
Classifier: Programming Language :: Python :: 3
Classifier: License :: OSI Approved :: MIT License
Classifier: Operating System :: OS Independent
Requires-Python: >=3.6
Requires-Dist: requests
Requires-Dist: json
Requires-Dist: getpass
Requires-Dist: pymongo
